nsk/__init__.py
nsk/bot/__init__.py
nsk/bot/dandoli.py
nsk/bot/mail_dealer.py
nsk/bot/microsoft.py
nsk/bot/web_access.py
nsk/bot/base/__init__.py
nsk/bot/base/bot.py
nsk/bot/base/meta.py
nsk/utils/__init__.py
nsk/utils/decorator.py
nsk/windows/__init__.py
nsk/windows/file_uploader.py
nsk/windows/base/__init__.py
nsk/windows/base/bot.py
nsk-2.4.3.dist-info/licenses/LICENSE
nsk-2.4.3.dist-info/METADATA
nsk-2.4.3.dist-info/WHEEL
nsk-2.4.3.dist-info/top_level.txt
nsk-2.4.3.dist-info/RECORD
