Metadata-Version: 2.4
Name: nsk
Version: 2.4.3
Summary: A Python library for NSK Automation
Author-email: Văn Ngoc Nhât Huy <nhathuyd4hp@gmail.com>
License: MIT
Requires-Python: >=3.12
License-File: LICENSE
Requires-Dist: office365-rest-python-client>=2.6.2
Requires-Dist: pandas>=2.2.3
Requires-Dist: pre-commit>=4.2.0
Requires-Dist: pydantic-settings>=2.9.1
Requires-Dist: pyinstaller>=6.13.0
Requires-Dist: pysharepoint>=0.1.7
Requires-Dist: pywinauto>=0.6.9
Requires-Dist: selenium>=4.32.0
Requires-Dist: xlwings>=0.33.14
Dynamic: license-file
